virsh_start_stop/__init__.py
virsh_start_stop/virsh_start_stop.py
virsh_start_stop-0.0.1.dist-info/LICENSE
virsh_start_stop-0.0.1.dist-info/METADATA
virsh_start_stop-0.0.1.dist-info/WHEEL
virsh_start_stop-0.0.1.dist-info/entry_points.txt
virsh_start_stop-0.0.1.dist-info/top_level.txt
virsh_start_stop-0.0.1.dist-info/RECORD
