Metadata-Version: 2.1
Name: virsh-start-stop
Version: 0.0.1
Summary: Utilize the python libvirt API to start and stop qemu-kvm machines in a blocking fashion
Home-page: https://github.com/avollmerhaus/virsh_start_stop
Author: Aljoscha Vollmerhaus
Author-email: pydev@aljoscha.vollmerhaus.net
License: UNKNOWN
Platform: UNKNOWN
Classifier: Programming Language :: Python :: 3
Classifier: License :: OSI Approved :: MIT License
Classifier: Operating System :: POSIX :: Linux
Classifier: Environment :: Console
Requires-Dist: libvirt-python
